komida/__init__.py
komida/__main__.py
komida/komida.py
komida-0.0.4.dist-info/LICENSE
komida-0.0.4.dist-info/WHEEL
komida-0.0.4.dist-info/METADATA
komida-0.0.4.dist-info/RECORD
